csp_llm/__init__.py
csp_llm/check_required_tools.py
csp_llm/constants.py
csp_llm/csp_llm.py
csp_llm/csp_tools.py
csp_llm/gui.py
csp_llm/llm_provider.py
csp_llm/main.py
csp_llm-0.2.2.dist-info/licenses/LICENSE
csp_llm-0.2.2.dist-info/METADATA
csp_llm-0.2.2.dist-info/WHEEL
csp_llm-0.2.2.dist-info/entry_points.txt
csp_llm-0.2.2.dist-info/top_level.txt
csp_llm-0.2.2.dist-info/RECORD
