Metadata-Version: 2.4
Name: csp_llm
Version: 0.2.2
Summary: Python app using llm via MCP for modeling and solving a csp problem in pycsp3
Author-email: Alain Kemgue <kemgue@cril.fr>
Maintainer-email: Alain Kemgue <kemgue@cril.fr>
License: MIT
Project-URL: Homepage, https://github.com/kemgue/csp_llm
Project-URL: Repository, https://github.com/kemgue/csp_llm
Project-URL: Bug Tracker, https://github.com/kemgue/csp_llm/issues
Keywords: pycsp3,csp,ai,llm,openai,anthropic
Classifier: Development Status :: 4 - Beta
Classifier: Intended Audience :: Developers
Classifier: License :: OSI Approved :: MIT License
Classifier: Operating System :: OS Independent
Classifier: Programming Language :: Python :: 3
Classifier: Programming Language :: Python :: 3.10
Classifier: Programming Language :: Python :: 3.11
Classifier: Programming Language :: Python :: 3.12
Classifier: Programming Language :: Python :: 3.13
Classifier: Topic :: Software Development :: Libraries :: Python Modules
Classifier: Topic :: Scientific/Engineering :: Artificial Intelligence
Requires-Python: >=3.10
License-File: LICENSE
Requires-Dist: streamlit>=1.28.0
Requires-Dist: streamlit-ace>=0.1.1
Requires-Dist: pycsp3>=2.3.0
Requires-Dist: openai>=1.0.0
Requires-Dist: anthropic>=0.7.0
Requires-Dist: python-dotenv>=1.0.1
Requires-Dist: aiohttp>=3.12.15
Provides-Extra: dev
Requires-Dist: pytest>=7.0.0; extra == "dev"
Requires-Dist: pytest-cov>=4.0.0; extra == "dev"
Requires-Dist: black>=23.0.0; extra == "dev"
Requires-Dist: flake8>=6.0.0; extra == "dev"
Requires-Dist: mypy>=1.0.0; extra == "dev"
Requires-Dist: pre-commit>=3.0.0; extra == "dev"
Provides-Extra: docs
Requires-Dist: sphinx>=5.0.0; extra == "docs"
Requires-Dist: sphinx-rtd-theme>=1.0.0; extra == "docs"
Dynamic: license-file
